mkdocs_render_otherfile_plugin/__init__.py
mkdocs_render_otherfile_plugin/plugin.py
mkdocs_render_otherfile_plugin-1.0.0.dist-info/LICENSE
mkdocs_render_otherfile_plugin-1.0.0.dist-info/METADATA
mkdocs_render_otherfile_plugin-1.0.0.dist-info/WHEEL
mkdocs_render_otherfile_plugin-1.0.0.dist-info/entry_points.txt
mkdocs_render_otherfile_plugin-1.0.0.dist-info/top_level.txt
mkdocs_render_otherfile_plugin-1.0.0.dist-info/RECORD
