Metadata-Version: 2.1
Name: mkdocs-render-otherfile-plugin
Version: 1.0.0
Summary: MkDocs Plugin to render other foramt files.
Home-page: https://github.com/FF1204/mkdocs-rendor-otherfile-plugin.git
Author: FF1204
Author-email: 120406191@qq.com
License: MIT
Keywords: mkdocs index rendor other file plugin
Platform: UNKNOWN
Classifier: Intended Audience :: Developers
Classifier: Intended Audience :: Information Technology
Classifier: License :: OSI Approved :: MIT License
Classifier: Programming Language :: Python
Classifier: Programming Language :: Python :: 3 :: Only
Classifier: Programming Language :: Python :: 3.5
Classifier: Programming Language :: Python :: 3.6
Classifier: Programming Language :: Python :: 3.7
Requires-Python: >=3.5
Requires-Dist: mkdocs (>=1.1)
